Metadata-Version: 2.1
Name: aws-sam-rw-cli
Version: 101.24.1
Summary: AWS SAM CLI is a CLI tool for local development and testing of Serverless applications. This build allows lambda to write to the mounted filesystem.
Home-page: https://github.com/OKRCentral/aws-sam-cli
Author: venkatramanka
Author-email: venkat@ally.io
License: Apache License 2.0
Keywords: AWS SAM CLI
Platform: UNKNOWN
Classifier: Development Status :: 5 - Production/Stable
Classifier: Environment :: Console
Classifier: Environment :: Other Environment
Classifier: Intended Audience :: Developers
Classifier: Intended Audience :: Information Technology
Classifier: License :: OSI Approved :: Apache Software License
Classifier: Operating System :: OS Independent
Classifier: Programming Language :: Python
Classifier: Programming Language :: Python :: 3.6
Classifier: Programming Language :: Python :: 3.7
Classifier: Programming Language :: Python :: 3.8
Classifier: Topic :: Internet
Classifier: Topic :: Software Development :: Build Tools
Classifier: Topic :: Utilities
Requires-Python: >=3.6, <=4.0, !=4.0
License-File: LICENSE
License-File: NOTICE
Requires-Dist: chevron (~=0.12)
Requires-Dist: click (~=7.1)
Requires-Dist: Flask (~=1.1.2)
Requires-Dist: boto3 (~=1.14)
Requires-Dist: jmespath (~=0.10.0)
Requires-Dist: PyYAML (~=5.3)
Requires-Dist: cookiecutter (~=1.7.2)
Requires-Dist: aws-sam-translator (==1.36.0)
Requires-Dist: docker (~=4.2.0)
Requires-Dist: dateparser (~=0.7)
Requires-Dist: requests (==2.23.0)
Requires-Dist: serverlessrepo (==0.1.10)
Requires-Dist: aws-lambda-builders (==1.4.0)
Requires-Dist: tomlkit (==0.7.0)
Requires-Dist: watchdog (==2.1.2)
Provides-Extra: dev
Requires-Dist: pylint (~=2.6.0) ; extra == 'dev'
Requires-Dist: coverage (==5.3) ; extra == 'dev'
Requires-Dist: pytest-cov (==2.10.1) ; extra == 'dev'
Requires-Dist: mypy (==0.790) ; extra == 'dev'
Requires-Dist: boto3-stubs[essential] (~=1.14) ; extra == 'dev'
Requires-Dist: pytest (==6.1.1) ; extra == 'dev'
Requires-Dist: parameterized (==0.7.4) ; extra == 'dev'
Requires-Dist: pytest-xdist (==2.1.0) ; extra == 'dev'
Requires-Dist: pytest-forked (==1.3.0) ; extra == 'dev'
Requires-Dist: pytest-timeout (==1.4.2) ; extra == 'dev'
Requires-Dist: pytest-rerunfailures (==9.1.1) ; extra == 'dev'
Requires-Dist: black (==20.8b1) ; extra == 'dev'
Provides-Extra: pre-dev
Requires-Dist: pylint (~=2.6.0) ; extra == 'pre-dev'
